document_clipper/__init__.py
document_clipper/exceptions.py
document_clipper/pdf.py
document_clipper/utils.py
document_clipper-1.2.1.dist-info/DESCRIPTION.rst
document_clipper-1.2.1.dist-info/METADATA
document_clipper-1.2.1.dist-info/RECORD
document_clipper-1.2.1.dist-info/WHEEL
document_clipper-1.2.1.dist-info/dependency_links.txt
document_clipper-1.2.1.dist-info/metadata.json
document_clipper-1.2.1.dist-info/top_level.txt
