Metadata-Version: 2.0
Name: document-clipper
Version: 1.2.1
Summary: A set of utility classes and functions to process documents with Python
Home-page: https://github.com/reclamador/document_clipper
Author: Nick Jaremek
Author-email: nick13jaremek@gmail.com
License: MIT license
Keywords: document_clipper
Platform: UNKNOWN
Classifier: Development Status :: 2 - Pre-Alpha
Classifier: Intended Audience :: Developers
Classifier: License :: OSI Approved :: MIT License
Classifier: Natural Language :: English
Classifier: Programming Language :: Python :: 2
Classifier: Programming Language :: Python :: 2.7
Requires-Dist: Pillow (==4.2.1)
Requires-Dist: PyPDF2 (==1.26.0)
Requires-Dist: beautifulsoup4 (==4.4.1)
Requires-Dist: lxml (==4.2.5)
Requires-Dist: pilkit (==2.0)
